[
  {
    "id": "6967dc28-0590-4727-90ab-2ac662c2dc10",
    "data": [
      {
        "text": "that\u0027s awesome ",
        "userDefined": false
      },
      {
        "text": "thank you",
        "userDefined": true
      }
    ],
    "isTemplate": false,
    "count": 1,
    "lang": "en-ca",
    "updated": 0
  },
  {
    "id": "574a209a-f3cf-4858-98ff-ca5c7c1242aa",
    "data": [
      {
        "text": "oh ",
        "userDefined": false
      },
      {
        "text": "well",
        "userDefined": true
      }
    ],
    "isTemplate": false,
    "count": 1,
    "lang": "en-ca",
    "updated": 0
  },
  {
    "id": "bf35d766-17e2-4d46-be56-728f530b8994",
    "data": [
      {
        "text": "that\u0027s a ",
        "userDefined": false
      },
      {
        "text": "good",
        "userDefined": true
      },
      {
        "text": " thing",
        "userDefined": false
      }
    ],
    "isTemplate": false,
    "count": 1,
    "lang": "en-ca",
    "updated": 0
  },
  {
    "id": "4c3754f0-1aad-4536-9237-657bb5a656a4",
    "data": [
      {
        "text": "that\u0027s very ",
        "userDefined": false
      },
      {
        "text": "good",
        "userDefined": true
      }
    ],
    "isTemplate": false,
    "count": 3,
    "lang": "en-ca",
    "updated": 0
  },
  {
    "id": "fdb82268-2af6-4dd5-a7a3-1861714f7382",
    "data": [
      {
        "text": "really ",
        "userDefined": false
      },
      {
        "text": "well",
        "userDefined": true
      }
    ],
    "isTemplate": false,
    "count": 1,
    "lang": "en-ca",
    "updated": 0
  },
  {
    "id": "fd6e5ae7-088f-4085-82f1-e89a7fd4ce46",
    "data": [
      {
        "text": "that is ",
        "userDefined": false
      },
      {
        "text": "nice",
        "userDefined": true
      }
    ],
    "isTemplate": false,
    "count": 1,
    "lang": "en-ca",
    "updated": 0
  },
  {
    "id": "5197daa7-85f1-4d16-aafc-c25fc2863f36",
    "data": [
      {
        "text": "that is ",
        "userDefined": false
      },
      {
        "text": "good",
        "userDefined": true
      }
    ],
    "isTemplate": false,
    "count": 1,
    "lang": "en-ca",
    "updated": 0
  },
  {
    "id": "bfa95f6c-7cec-4689-9a07-24a0abd0c820",
    "data": [
      {
        "text": "sweet",
        "userDefined": false
      }
    ],
    "isTemplate": false,
    "count": 2,
    "lang": "en-ca",
    "updated": 0
  },
  {
    "id": "95dfbd4e-b396-4c5e-b62c-31d26c2cd943",
    "data": [
      {
        "text": "that\u0027s better",
        "userDefined": false
      }
    ],
    "isTemplate": false,
    "count": 1,
    "lang": "en-ca",
    "updated": 0
  },
  {
    "id": "27d21311-fff4-4545-9cd9-9e456e203769",
    "data": [
      {
        "text": "it",
        "userDefined": true
      },
      {
        "text": "\u0027s good",
        "userDefined": false
      }
    ],
    "isTemplate": false,
    "count": 3,
    "lang": "en-ca",
    "updated": 0
  },
  {
    "id": "3d0d645d-4014-4c8c-9b4e-674a2840c79d",
    "data": [
      {
        "text": "that\u0027s sweet ",
        "userDefined": false
      },
      {
        "text": "of",
        "userDefined": true
      },
      {
        "text": " you",
        "userDefined": false
      }
    ],
    "isTemplate": false,
    "count": 1,
    "lang": "en-ca",
    "updated": 0
  },
  {
    "id": "6f88afa4-5f8a-4780-9802-e2902736ac63",
    "data": [
      {
        "text": "it",
        "userDefined": true
      },
      {
        "text": " was ",
        "userDefined": false
      },
      {
        "text": "good",
        "userDefined": true
      }
    ],
    "isTemplate": false,
    "count": 1,
    "lang": "en-ca",
    "updated": 0
  },
  {
    "id": "cf5ca63b-d6cb-4a89-b1fc-20c41bf09c52",
    "data": [
      {
        "text": "that\u0027s ",
        "userDefined": false
      },
      {
        "text": "nice",
        "userDefined": true
      },
      {
        "text": " ",
        "userDefined": false
      },
      {
        "text": "of",
        "userDefined": true
      },
      {
        "text": " you",
        "userDefined": false
      }
    ],
    "isTemplate": false,
    "count": 1,
    "lang": "en-ca",
    "updated": 0
  },
  {
    "id": "1424c785-b932-4568-bddb-9ee12e57a297",
    "data": [
      {
        "text": "that was awesome",
        "userDefined": false
      }
    ],
    "isTemplate": false,
    "count": 1,
    "lang": "en-ca",
    "updated": 0
  },
  {
    "id": "2c458fc4-0a22-4286-b1ef-da629d3b7d25",
    "data": [
      {
        "text": "cool",
        "userDefined": false
      }
    ],
    "isTemplate": false,
    "count": 1,
    "lang": "en-ca",
    "updated": 0
  },
  {
    "id": "28e5e15d-a81f-4f73-b849-28bd63fecb23",
    "data": [
      {
        "text": "this is awesome",
        "userDefined": false
      }
    ],
    "isTemplate": false,
    "count": 1,
    "lang": "en-ca",
    "updated": 0
  },
  {
    "id": "23f0bfd1-658b-4fb2-91a6-009fbdc62407",
    "data": [
      {
        "text": "that\u0027s wonderful",
        "userDefined": false
      }
    ],
    "isTemplate": false,
    "count": 1,
    "lang": "en-ca",
    "updated": 0
  },
  {
    "id": "f6e0123b-18ba-47b2-a631-ab8238ff5a19",
    "data": [
      {
        "text": "straight",
        "userDefined": false
      }
    ],
    "isTemplate": false,
    "count": 1,
    "lang": "en-ca",
    "updated": 0
  },
  {
    "id": "51d95aaa-a49b-456b-8d74-180bedcf1dfd",
    "data": [
      {
        "text": "so ",
        "userDefined": false
      },
      {
        "text": "cool",
        "userDefined": false
      }
    ],
    "isTemplate": false,
    "count": 1,
    "lang": "en-ca",
    "updated": 0
  },
  {
    "id": "ff0fb4d8-dd58-4797-9455-62b313739e91",
    "data": [
      {
        "text": "good",
        "userDefined": true
      }
    ],
    "isTemplate": false,
    "count": 2,
    "lang": "en-ca",
    "updated": 0
  },
  {
    "id": "6f3524e1-da23-42e6-85e3-075ed980418c",
    "data": [
      {
        "text": "that\u0027s ",
        "userDefined": false
      },
      {
        "text": "great",
        "userDefined": true
      }
    ],
    "isTemplate": false,
    "count": 4,
    "lang": "en-ca",
    "updated": 0
  },
  {
    "id": "cef32dcc-b496-485c-ab6d-71ebf7fc13dd",
    "data": [
      {
        "text": "excellent",
        "userDefined": false
      }
    ],
    "isTemplate": false,
    "count": 1,
    "lang": "en-ca",
    "updated": 0
  },
  {
    "id": "33294966-ceb1-438d-89c5-66e0c9ccfb2b",
    "data": [
      {
        "text": "that\u0027s not ",
        "userDefined": false
      },
      {
        "text": "bad",
        "userDefined": true
      }
    ],
    "isTemplate": false,
    "count": 1,
    "lang": "en-ca",
    "updated": 0
  },
  {
    "id": "3e937464-90d5-4377-ac81-d267a5b250ff",
    "data": [
      {
        "text": "that is wonderful",
        "userDefined": false
      }
    ],
    "isTemplate": false,
    "count": 1,
    "lang": "en-ca",
    "updated": 0
  },
  {
    "id": "c6afc7b7-ec35-4238-b649-134aa09031a4",
    "data": [
      {
        "text": "much better",
        "userDefined": false
      }
    ],
    "isTemplate": false,
    "count": 1,
    "lang": "en-ca",
    "updated": 0
  },
  {
    "id": "95350efd-4b64-48a1-997e-477a317d1184",
    "data": [
      {
        "text": "splendid",
        "userDefined": false
      }
    ],
    "isTemplate": false,
    "count": 1,
    "lang": "en-ca",
    "updated": 0
  },
  {
    "id": "28a2ddab-eb9c-4235-934a-9a9a939ee363",
    "data": [
      {
        "text": "I\u0027m",
        "userDefined": true
      },
      {
        "text": " glad to hear that",
        "userDefined": false
      }
    ],
    "isTemplate": false,
    "count": 1,
    "lang": "en-ca",
    "updated": 0
  },
  {
    "id": "4536d83e-c82b-49fe-bbfd-f6c0a46ad5ab",
    "data": [
      {
        "text": "terrific",
        "userDefined": false
      }
    ],
    "isTemplate": false,
    "count": 2,
    "lang": "en-ca",
    "updated": 0
  },
  {
    "id": "bc32ace5-3277-4b31-a739-153004607544",
    "data": [
      {
        "text": "very ",
        "userDefined": false
      },
      {
        "text": "well",
        "userDefined": true
      }
    ],
    "isTemplate": false,
    "count": 1,
    "lang": "en-ca",
    "updated": 0
  },
  {
    "id": "53c412a1-225e-46af-a503-43b038c4cf04",
    "data": [
      {
        "text": "that\u0027s perfect",
        "userDefined": false
      }
    ],
    "isTemplate": false,
    "count": 1,
    "lang": "en-ca",
    "updated": 0
  },
  {
    "id": "14f5b585-be25-49b6-8e0c-4334d8ddd846",
    "data": [
      {
        "text": "good",
        "userDefined": true
      },
      {
        "text": " very ",
        "userDefined": false
      },
      {
        "text": "good",
        "userDefined": true
      }
    ],
    "isTemplate": false,
    "count": 1,
    "lang": "en-ca",
    "updated": 0
  },
  {
    "id": "c7a7daa3-63c1-406c-9185-0704144a3e14",
    "data": [
      {
        "text": "that\u0027s great",
        "userDefined": false
      }
    ],
    "isTemplate": false,
    "count": 1,
    "lang": "en-ca",
    "updated": 0
  },
  {
    "id": "3cb3c6b3-af57-40fa-a631-e9bcbbbcf50b",
    "data": [
      {
        "text": "that was amazing",
        "userDefined": false
      }
    ],
    "isTemplate": false,
    "count": 1,
    "lang": "en-ca",
    "updated": 0
  },
  {
    "id": "96389ea0-da6b-41a4-80c7-5a782db000df",
    "data": [
      {
        "text": "that\u0027s really ",
        "userDefined": false
      },
      {
        "text": "nice",
        "userDefined": true
      }
    ],
    "isTemplate": false,
    "count": 1,
    "lang": "en-ca",
    "updated": 0
  },
  {
    "id": "eb58be74-5970-4852-8104-3ea8b4435ea8",
    "data": [
      {
        "text": "so sweet ",
        "userDefined": false
      },
      {
        "text": "of",
        "userDefined": true
      },
      {
        "text": " you",
        "userDefined": false
      }
    ],
    "isTemplate": false,
    "count": 1,
    "lang": "en-ca",
    "updated": 0
  },
  {
    "id": "4a4bb5ed-794b-4f13-8fbd-f9ee1a9ab76c",
    "data": [
      {
        "text": "that\u0027s amazing",
        "userDefined": false
      }
    ],
    "isTemplate": false,
    "count": 1,
    "lang": "en-ca",
    "updated": 0
  },
  {
    "id": "ad6c02af-f9cb-48c0-9717-0c56b1416617",
    "data": [
      {
        "text": "good",
        "userDefined": true
      },
      {
        "text": " to know",
        "userDefined": false
      }
    ],
    "isTemplate": false,
    "count": 1,
    "lang": "en-ca",
    "updated": 0
  },
  {
    "id": "9c9f0985-7399-4bfc-8b4e-7f51baa361ee",
    "data": [
      {
        "text": "that\u0027s awesome",
        "userDefined": false
      }
    ],
    "isTemplate": false,
    "count": 1,
    "lang": "en-ca",
    "updated": 0
  },
  {
    "id": "70ff1b1f-351b-49dd-94fb-abcd66847368",
    "data": [
      {
        "text": "marvelous",
        "userDefined": false
      }
    ],
    "isTemplate": false,
    "count": 1,
    "lang": "en-ca",
    "updated": 0
  },
  {
    "id": "3ead1464-4bcc-4213-964c-9d6ec0801862",
    "data": [
      {
        "text": "ok ",
        "userDefined": false
      },
      {
        "text": "good",
        "userDefined": true
      }
    ],
    "isTemplate": false,
    "count": 1,
    "lang": "en-ca",
    "updated": 0
  },
  {
    "id": "8e070cdd-bd64-45af-8f9f-b24534af6357",
    "data": [
      {
        "text": "very then",
        "userDefined": false
      }
    ],
    "isTemplate": false,
    "count": 1,
    "lang": "en-ca",
    "updated": 0
  },
  {
    "id": "ad4ba542-9002-4d12-bbf2-f28a56beec4c",
    "data": [
      {
        "text": "nice",
        "userDefined": true
      }
    ],
    "isTemplate": false,
    "count": 1,
    "lang": "en-ca",
    "updated": 0
  },
  {
    "id": "cbe76560-d629-42e7-a1fb-43e77e385567",
    "data": [
      {
        "text": "that\u0027s very ",
        "userDefined": false
      },
      {
        "text": "nice",
        "userDefined": true
      }
    ],
    "isTemplate": false,
    "count": 2,
    "lang": "en-ca",
    "updated": 0
  },
  {
    "id": "37d16039-8c1b-4891-a293-5e51a4361be5",
    "data": [
      {
        "text": "that\u0027s very ",
        "userDefined": false
      },
      {
        "text": "nice",
        "userDefined": true
      },
      {
        "text": " ",
        "userDefined": false
      },
      {
        "text": "of",
        "userDefined": true
      },
      {
        "text": " you",
        "userDefined": false
      }
    ],
    "isTemplate": false,
    "count": 1,
    "lang": "en-ca",
    "updated": 0
  },
  {
    "id": "48f031c3-8bc0-41f5-b9f8-64dbcdd632f7",
    "data": [
      {
        "text": "this is ",
        "userDefined": false
      },
      {
        "text": "great",
        "userDefined": true
      }
    ],
    "isTemplate": false,
    "count": 1,
    "lang": "en-ca",
    "updated": 0
  },
  {
    "id": "9573ec1a-790c-4ba8-9691-7dd3b58c4bc8",
    "data": [
      {
        "text": "very nice",
        "userDefined": false
      }
    ],
    "isTemplate": false,
    "count": 1,
    "lang": "en-ca",
    "updated": 0
  },
  {
    "id": "d8364409-6363-42b5-8901-fa120446b7a2",
    "data": [
      {
        "text": "not too ",
        "userDefined": false
      },
      {
        "text": "bad",
        "userDefined": true
      }
    ],
    "isTemplate": false,
    "count": 2,
    "lang": "en-ca",
    "updated": 0
  },
  {
    "id": "e2066555-f0ed-4699-93ed-ecde60b6250e",
    "data": [
      {
        "text": "it\u0027s very good",
        "userDefined": false
      }
    ],
    "isTemplate": false,
    "count": 1,
    "lang": "en-ca",
    "updated": 0
  },
  {
    "id": "0e19174e-d9ab-44ed-86fb-d0167cd57798",
    "data": [
      {
        "text": "really ",
        "userDefined": false
      },
      {
        "text": "good",
        "userDefined": true
      }
    ],
    "isTemplate": false,
    "count": 2,
    "lang": "en-ca",
    "updated": 0
  },
  {
    "id": "c52ece52-3b5a-494b-851d-e9cd3c371324",
    "data": [
      {
        "text": "it",
        "userDefined": true
      },
      {
        "text": " is ",
        "userDefined": false
      },
      {
        "text": "fine",
        "userDefined": true
      }
    ],
    "isTemplate": false,
    "count": 1,
    "lang": "en-ca",
    "updated": 0
  },
  {
    "id": "4d079f4c-d0bb-43dd-8dd3-2863866dc0ef",
    "data": [
      {
        "text": "it\u0027s",
        "userDefined": true
      },
      {
        "text": " ",
        "userDefined": false
      },
      {
        "text": "great",
        "userDefined": true
      }
    ],
    "isTemplate": false,
    "count": 1,
    "lang": "en-ca",
    "updated": 0
  },
  {
    "id": "c36b2bb7-93b9-4409-a468-9e7b2e41ca2f",
    "data": [
      {
        "text": "fine",
        "userDefined": true
      }
    ],
    "isTemplate": false,
    "count": 1,
    "lang": "en-ca",
    "updated": 0
  },
  {
    "id": "8f2ad2d2-10a6-4307-8dc4-87b444904d28",
    "data": [
      {
        "text": "that\u0027s much better",
        "userDefined": false
      }
    ],
    "isTemplate": false,
    "count": 1,
    "lang": "en-ca",
    "updated": 0
  },
  {
    "id": "f620a3e1-2f1a-45f0-b675-92c999059bb6",
    "data": [
      {
        "text": "that was pretty ",
        "userDefined": false
      },
      {
        "text": "good",
        "userDefined": true
      }
    ],
    "isTemplate": false,
    "count": 1,
    "lang": "en-ca",
    "updated": 0
  },
  {
    "id": "03fef0cb-3a3d-4ed3-9cc9-bb7ae1515cfb",
    "data": [
      {
        "text": "glad to hear that",
        "userDefined": false
      }
    ],
    "isTemplate": false,
    "count": 1,
    "lang": "en-ca",
    "updated": 0
  },
  {
    "id": "09a7df22-0357-4946-bada-fe912cfc64bc",
    "data": [
      {
        "text": "wonderful",
        "userDefined": false
      }
    ],
    "isTemplate": false,
    "count": 1,
    "lang": "en-ca",
    "updated": 0
  },
  {
    "id": "17eb17d4-c4e0-4065-a737-7796331c6832",
    "data": [
      {
        "text": "that\u0027s ",
        "userDefined": false
      },
      {
        "text": "nice",
        "userDefined": true
      }
    ],
    "isTemplate": false,
    "count": 2,
    "lang": "en-ca",
    "updated": 0
  },
  {
    "id": "f06b6db5-3a8b-4c7e-9c60-9ec9211d500d",
    "data": [
      {
        "text": "it",
        "userDefined": true
      },
      {
        "text": " is ",
        "userDefined": false
      },
      {
        "text": "good",
        "userDefined": true
      }
    ],
    "isTemplate": false,
    "count": 1,
    "lang": "en-ca",
    "updated": 0
  },
  {
    "id": "9eaa6dc0-ca64-471b-b187-2dfcd3ee6e2d",
    "data": [
      {
        "text": "great",
        "userDefined": true
      }
    ],
    "isTemplate": false,
    "count": 2,
    "lang": "en-ca",
    "updated": 0
  },
  {
    "id": "1a8a990a-01b0-40ae-b1e4-d7c9e8b8b00d",
    "data": [
      {
        "text": "pretty ",
        "userDefined": false
      },
      {
        "text": "good",
        "userDefined": true
      }
    ],
    "isTemplate": false,
    "count": 1,
    "lang": "en-ca",
    "updated": 0
  },
  {
    "id": "cfa9b5f2-ed87-4345-85e5-62e507488049",
    "data": [
      {
        "text": "okay good",
        "userDefined": false
      }
    ],
    "isTemplate": false,
    "count": 1,
    "lang": "en-ca",
    "updated": 0
  },
  {
    "id": "44d5607c-12c1-4fb4-a457-cd895395651b",
    "data": [
      {
        "text": "really ",
        "userDefined": false
      },
      {
        "text": "nice",
        "userDefined": true
      }
    ],
    "isTemplate": false,
    "count": 1,
    "lang": "en-ca",
    "updated": 0
  },
  {
    "id": "3aacb6b2-c79a-4f7b-83f4-75737b3e2d29",
    "data": [
      {
        "text": "this is ",
        "userDefined": false
      },
      {
        "text": "good",
        "userDefined": true
      }
    ],
    "isTemplate": false,
    "count": 1,
    "lang": "en-ca",
    "updated": 0
  },
  {
    "id": "d2811f1a-5660-41f4-87e6-ef4ec02c5129",
    "data": [
      {
        "text": "it\u0027s fine",
        "userDefined": false
      }
    ],
    "isTemplate": false,
    "count": 1,
    "lang": "en-ca",
    "updated": 0
  },
  {
    "id": "8aea2013-a62f-4884-991b-4d3cb2241fd0",
    "data": [
      {
        "text": "that\u0027s pretty ",
        "userDefined": false
      },
      {
        "text": "good",
        "userDefined": true
      }
    ],
    "isTemplate": false,
    "count": 1,
    "lang": "en-ca",
    "updated": 0
  },
  {
    "id": "52a00f45-afc3-4b3b-993d-42b7bcd026bf",
    "data": [
      {
        "text": "very ",
        "userDefined": false
      },
      {
        "text": "nice",
        "userDefined": true
      }
    ],
    "isTemplate": false,
    "count": 1,
    "lang": "en-ca",
    "updated": 0
  },
  {
    "id": "d48f620c-4d24-43bd-8361-49ae32cde471",
    "data": [
      {
        "text": "fantastic",
        "userDefined": false
      }
    ],
    "isTemplate": false,
    "count": 1,
    "lang": "en-ca",
    "updated": 0
  },
  {
    "id": "61c1e5e0-04da-4e85-9770-02e5f037c3a3",
    "data": [
      {
        "text": "that\u0027s cute",
        "userDefined": false
      }
    ],
    "isTemplate": false,
    "count": 1,
    "lang": "en-ca",
    "updated": 0
  },
  {
    "id": "0cf83892-84a0-4937-b521-ff9529f45f05",
    "data": [
      {
        "text": "that\u0027s ",
        "userDefined": false
      },
      {
        "text": "fine",
        "userDefined": true
      }
    ],
    "isTemplate": false,
    "count": 1,
    "lang": "en-ca",
    "updated": 0
  },
  {
    "id": "b41f8580-176c-43b2-946e-f0819047f96c",
    "data": [
      {
        "text": "that\u0027s a ",
        "userDefined": false
      },
      {
        "text": "good",
        "userDefined": true
      },
      {
        "text": " idea",
        "userDefined": false
      }
    ],
    "isTemplate": false,
    "count": 1,
    "lang": "en-ca",
    "updated": 0
  },
  {
    "id": "dbe4f502-8528-49f2-a8ec-a2219477d395",
    "data": [
      {
        "text": "glad to hear ",
        "userDefined": false
      },
      {
        "text": "it",
        "userDefined": true
      }
    ],
    "isTemplate": false,
    "count": 1,
    "lang": "en-ca",
    "updated": 0
  },
  {
    "id": "646742ae-6a8f-44ca-a469-c091ffe1779e",
    "data": [
      {
        "text": "not ",
        "userDefined": false
      },
      {
        "text": "bad",
        "userDefined": true
      }
    ],
    "isTemplate": false,
    "count": 1,
    "lang": "en-ca",
    "updated": 0
  },
  {
    "id": "1afad313-806f-4ed6-b96b-7c90a3697804",
    "data": [
      {
        "text": "super fantastic",
        "userDefined": false
      }
    ],
    "isTemplate": false,
    "count": 1,
    "lang": "en-ca",
    "updated": 0
  },
  {
    "id": "4c8748f6-c8b6-43fc-af65-5afa9bf05a38",
    "data": [
      {
        "text": "good",
        "userDefined": true
      },
      {
        "text": " for you",
        "userDefined": false
      }
    ],
    "isTemplate": false,
    "count": 1,
    "lang": "en-ca",
    "updated": 0
  },
  {
    "id": "c2386c65-68d9-4d00-9574-e1877e61b1c8",
    "data": [
      {
        "text": "it\u0027s amazing",
        "userDefined": false
      }
    ],
    "isTemplate": false,
    "count": 1,
    "lang": "en-ca",
    "updated": 0
  },
  {
    "id": "a5d9542a-e3e8-4685-bfda-d9a457c504e5",
    "data": [
      {
        "text": "very ",
        "userDefined": false
      },
      {
        "text": "good",
        "userDefined": true
      }
    ],
    "isTemplate": false,
    "count": 1,
    "lang": "en-ca",
    "updated": 0
  },
  {
    "id": "7f5ce5c6-6b1c-496d-8034-946f70b21d03",
    "data": [
      {
        "text": "that is awesome",
        "userDefined": false
      }
    ],
    "isTemplate": false,
    "count": 2,
    "lang": "en-ca",
    "updated": 0
  },
  {
    "id": "4be9bf98-034e-410a-b124-a10b9e74d596",
    "data": [
      {
        "text": "it\u0027s",
        "userDefined": true
      },
      {
        "text": " very good",
        "userDefined": false
      }
    ],
    "isTemplate": false,
    "count": 1,
    "lang": "en-ca",
    "updated": 0
  },
  {
    "id": "dd28f692-e69b-49eb-9c40-6b91a217820e",
    "data": [
      {
        "text": "it\u0027s",
        "userDefined": true
      },
      {
        "text": " perfect",
        "userDefined": false
      }
    ],
    "isTemplate": false,
    "count": 2,
    "lang": "en-ca",
    "updated": 0
  },
  {
    "id": "21155d09-14d6-4386-8569-459510535641",
    "data": [
      {
        "text": "that was good",
        "userDefined": false
      }
    ],
    "isTemplate": false,
    "count": 1,
    "lang": "en-ca",
    "updated": 0
  },
  {
    "id": "5c3f9ecc-90d3-4230-9c9d-4831454e2fdc",
    "data": [
      {
        "text": "no ",
        "userDefined": false
      },
      {
        "text": "it",
        "userDefined": true
      },
      {
        "text": "\u0027s ",
        "userDefined": false
      },
      {
        "text": "okay",
        "userDefined": true
      }
    ],
    "isTemplate": false,
    "count": 1,
    "lang": "en-ca",
    "updated": 0
  },
  {
    "id": "59ae484a-4163-44a3-9a6d-7f32125a2846",
    "data": [
      {
        "text": "super",
        "userDefined": false
      }
    ],
    "isTemplate": false,
    "count": 1,
    "lang": "en-ca",
    "updated": 0
  },
  {
    "id": "cb63ceba-4908-4a33-b7c5-ab78080ed89f",
    "data": [
      {
        "text": "good",
        "userDefined": true
      },
      {
        "text": " thing",
        "userDefined": false
      }
    ],
    "isTemplate": false,
    "count": 1,
    "lang": "en-ca",
    "updated": 0
  },
  {
    "id": "47b59284-0dd9-4fee-bc8d-237984debe41",
    "data": [
      {
        "text": "that was cute",
        "userDefined": false
      }
    ],
    "isTemplate": false,
    "count": 1,
    "lang": "en-ca",
    "updated": 0
  },
  {
    "id": "276a8f3f-56de-4ca0-bb25-b9c6938bf513",
    "data": [
      {
        "text": "that\u0027s fantastic",
        "userDefined": false
      }
    ],
    "isTemplate": false,
    "count": 1,
    "lang": "en-ca",
    "updated": 0
  },
  {
    "id": "f944545d-c739-4400-9e36-17d5fe16d6e9",
    "data": [
      {
        "text": "perfect",
        "userDefined": false
      }
    ],
    "isTemplate": false,
    "count": 2,
    "lang": "en-ca",
    "updated": 0
  },
  {
    "id": "aef63ee1-d284-4085-a54e-018dea7560ff",
    "data": [
      {
        "text": "pleasant",
        "userDefined": false
      }
    ],
    "isTemplate": false,
    "count": 1,
    "lang": "en-ca",
    "updated": 0
  },
  {
    "id": "5ffc5768-f5fc-4e15-aaed-9fef1bf8d8b6",
    "data": [
      {
        "text": "it",
        "userDefined": true
      },
      {
        "text": "\u0027s great",
        "userDefined": false
      }
    ],
    "isTemplate": false,
    "count": 4,
    "lang": "en-ca",
    "updated": 0
  },
  {
    "id": "3a240d84-0036-453d-a72d-6c3cb8ee6ab3",
    "data": [
      {
        "text": "that was very ",
        "userDefined": false
      },
      {
        "text": "good",
        "userDefined": true
      }
    ],
    "isTemplate": false,
    "count": 1,
    "lang": "en-ca",
    "updated": 0
  },
  {
    "id": "68a838a6-3afd-4870-975f-2e219cb8cd1c",
    "data": [
      {
        "text": "that\u0027s fine",
        "userDefined": false
      }
    ],
    "isTemplate": false,
    "count": 1,
    "lang": "en-ca",
    "updated": 0
  },
  {
    "id": "e2c9f8d2-3514-40d9-8cad-789f38173267",
    "data": [
      {
        "text": "amazing",
        "userDefined": false
      }
    ],
    "isTemplate": false,
    "count": 1,
    "lang": "en-ca",
    "updated": 0
  },
  {
    "id": "444060ee-9e92-49fc-b740-5c392e78a783",
    "data": [
      {
        "text": "that\u0027s really ",
        "userDefined": false
      },
      {
        "text": "good",
        "userDefined": true
      }
    ],
    "isTemplate": false,
    "count": 1,
    "lang": "en-ca",
    "updated": 0
  },
  {
    "id": "a08a2fcb-3845-4c53-bcaf-110f1eef826a",
    "data": [
      {
        "text": "so ",
        "userDefined": false
      },
      {
        "text": "good",
        "userDefined": true
      }
    ],
    "isTemplate": false,
    "count": 1,
    "lang": "en-ca",
    "updated": 0
  },
  {
    "id": "d6a474ad-461d-4d88-a889-6170661bfaa0",
    "data": [
      {
        "text": "it\u0027s awesome",
        "userDefined": false
      }
    ],
    "isTemplate": false,
    "count": 1,
    "lang": "en-ca",
    "updated": 0
  }
]