[
  {
    "id": "673a9e86-f6a0-4f28-890c-8ca2683b1ec8",
    "data": [
      {
        "text": "it\u0027s",
        "userDefined": false
      },
      {
        "text": " ",
        "userDefined": false
      },
      {
        "text": "good",
        "userDefined": false
      },
      {
        "text": " to see you too",
        "userDefined": false
      }
    ],
    "isTemplate": false,
    "count": 1,
    "lang": "en-us",
    "updated": 0
  },
  {
    "id": "750df0d8-d848-49d7-9ef4-badba4cdd47f",
    "data": [
      {
        "text": "it\u0027s",
        "userDefined": false
      },
      {
        "text": " ",
        "userDefined": false
      },
      {
        "text": "nice",
        "userDefined": false
      },
      {
        "text": " to see you",
        "userDefined": false
      }
    ],
    "isTemplate": false,
    "count": 1,
    "lang": "en-us",
    "updated": 0
  },
  {
    "id": "8f633f62-ea46-4761-8f82-3277146fd1f5",
    "data": [
      {
        "text": "good",
        "userDefined": false
      },
      {
        "text": " to see you again",
        "userDefined": false
      }
    ],
    "isTemplate": false,
    "count": 2,
    "lang": "en-us",
    "updated": 0
  },
  {
    "id": "c5fa48b5-dcd7-4303-9177-752e96d7f2e1",
    "data": [
      {
        "text": "nice",
        "userDefined": false
      },
      {
        "text": " to see you again",
        "userDefined": false
      }
    ],
    "isTemplate": false,
    "count": 1,
    "lang": "en-us",
    "updated": 0
  },
  {
    "id": "2c7934f3-151a-4784-bf73-82b9dd152d5b",
    "data": [
      {
        "text": "great to see you too",
        "userDefined": false
      }
    ],
    "isTemplate": false,
    "count": 0,
    "lang": "en-us",
    "updated": 0
  },
  {
    "id": "f9ea6b61-1cfa-4124-8a06-10ab2689f670",
    "data": [
      {
        "text": "great to see you again",
        "userDefined": false
      }
    ],
    "isTemplate": false,
    "count": 0,
    "lang": "en-us",
    "updated": 0
  },
  {
    "id": "7e51c560-777f-48be-a880-14e2cf69a06c",
    "data": [
      {
        "text": "always a pleasure to see you",
        "userDefined": false
      }
    ],
    "isTemplate": false,
    "count": 0,
    "lang": "en-us",
    "updated": 0
  },
  {
    "id": "0bafa0c2-f748-4338-82d1-6b0d3fb0ee91",
    "data": [
      {
        "text": "great to see you",
        "userDefined": false
      }
    ],
    "isTemplate": false,
    "count": 1,
    "lang": "en-us",
    "updated": 0
  },
  {
    "id": "1b4bfd32-1be9-429d-8821-8a2b19ced38f",
    "data": [
      {
        "text": "how ",
        "userDefined": false
      },
      {
        "text": "good",
        "userDefined": false
      },
      {
        "text": " ",
        "userDefined": false
      },
      {
        "text": "it",
        "userDefined": false
      },
      {
        "text": " is to see you",
        "userDefined": false
      }
    ],
    "isTemplate": false,
    "count": 1,
    "lang": "en-us",
    "updated": 0
  },
  {
    "id": "547baa4d-ff47-4664-a42a-e57c7dbe24c4",
    "data": [
      {
        "text": "it\u0027s",
        "userDefined": false
      },
      {
        "text": " ",
        "userDefined": false
      },
      {
        "text": "good",
        "userDefined": false
      },
      {
        "text": " to see you",
        "userDefined": false
      }
    ],
    "isTemplate": false,
    "count": 0,
    "lang": "en-us",
    "updated": 0
  },
  {
    "id": "30b92a81-1270-45a3-92ae-1db3f4ee49ad",
    "data": [
      {
        "text": "good",
        "userDefined": false
      },
      {
        "text": " to see you",
        "userDefined": false
      }
    ],
    "isTemplate": false,
    "count": 1,
    "lang": "en-us",
    "updated": 0
  },
  {
    "id": "c0fab706-f203-4ff0-b04c-4523c7a455e1",
    "data": [
      {
        "text": "I\u0027m glad to see you",
        "userDefined": false
      }
    ],
    "isTemplate": false,
    "count": 0,
    "lang": "en-us",
    "updated": 0
  },
  {
    "id": "e36d96b4-7dc2-4ea0-8a3c-51c9670bddb7",
    "data": [
      {
        "text": "nice",
        "userDefined": false
      },
      {
        "text": " to see you",
        "userDefined": false
      }
    ],
    "isTemplate": false,
    "count": 0,
    "lang": "en-us",
    "updated": 0
  },
  {
    "id": "fa2f69dc-c775-4e4d-9c56-79f7d3a7317f",
    "data": [
      {
        "text": "glad to see you",
        "userDefined": false
      }
    ],
    "isTemplate": false,
    "count": 0,
    "lang": "en-us",
    "updated": 0
  },
  {
    "id": "cf6bb8f0-7bb1-4afe-85b9-09131911f1b5",
    "data": [
      {
        "text": "I am glad to see you again",
        "userDefined": false
      }
    ],
    "isTemplate": false,
    "count": 0,
    "lang": "en-us",
    "updated": 0
  },
  {
    "id": "e2523004-6f2d-4dc2-911b-f776b88b3c5c",
    "data": [
      {
        "text": "glad to see you too",
        "userDefined": false
      }
    ],
    "isTemplate": false,
    "count": 1,
    "lang": "en-us",
    "updated": 0
  },
  {
    "id": "fa9b14e6-daec-422c-80c5-a6230890959d",
    "data": [
      {
        "text": "lovely",
        "userDefined": false
      },
      {
        "text": " to see you",
        "userDefined": false
      }
    ],
    "isTemplate": false,
    "count": 0,
    "lang": "en-us",
    "updated": 0
  }
]